iris_cli/__init__.py
iris_cli/iris.py
iris_ai_cli-0.1.8.dist-info/METADATA
iris_ai_cli-0.1.8.dist-info/WHEEL
iris_ai_cli-0.1.8.dist-info/entry_points.txt
iris_ai_cli-0.1.8.dist-info/top_level.txt
iris_ai_cli-0.1.8.dist-info/RECORD
