Metadata-Version: 2.4
Name: iris-ai-cli
Version: 0.1.8
Summary: Iris an ai CLI tool.
Author-email: Ayaan Khan <ayaan.khan2812@gmail.com>
Project-URL: Repository, https://github.com/ayaankhan28/iris-cli
Project-URL: Homepage, https://github.com/ayaankhan28/iris-cli
Project-URL: Bug Tracker, https://github.com/ayaankhan28/iris-cli/issues
Keywords: ai,cli,groq,iris,assistant
Classifier: Development Status :: 3 - Alpha
Classifier: Intended Audience :: Developers
Classifier: Operating System :: OS Independent
Classifier: Programming Language :: Python :: 3
Classifier: Programming Language :: Python :: 3.7
Classifier: Programming Language :: Python :: 3.8
Classifier: Programming Language :: Python :: 3.9
Classifier: Programming Language :: Python :: 3.10
Classifier: Programming Language :: Python :: 3.11
Classifier: Programming Language :: Python :: 3.12
Classifier: Topic :: Software Development :: Libraries :: Python Modules
Classifier: Topic :: Scientific/Engineering :: Artificial Intelligence
Requires-Python: >=3.7
Requires-Dist: groq
Requires-Dist: rich
Requires-Dist: psutil
Requires-Dist: gitpython
